contract/__init__.py
contract/admin.py
contract/apps.py
contract/config.py
contract/exceptions.py
contract/models.py
contract/schema.py
contract/services.py
contract/signals.py
contract/tasks.py
contract/urls.py
contract/utils.py
contract/views.py
contract/gql/__init__.py
contract/gql/gql_types.py
contract/gql/gql_mutations/__init__.py
contract/gql/gql_mutations/contract_details_mutations.py
contract/gql/gql_mutations/contract_mutations.py
contract/gql/gql_mutations/input_types.py
contract/gql/gql_mutations/mutations.py
contract/migrations/0001_initial.py
contract/migrations/0002_auto_20201221_1547.py
contract/migrations/0003_auto_20201222_1044.py
contract/migrations/0004_auto_20201222_1424.py
contract/migrations/0005_auto_20201228_1151.py
contract/migrations/0006_auto_20201228_1218.py
contract/migrations/0007_auto_20201228_1310.py
contract/migrations/0008_auto_20201230_1052.py
contract/migrations/0009_auto_20210118_1427.py
contract/migrations/0010_auto_20210119_1204.py
contract/migrations/0011_contractmutation.py
contract/migrations/0012_contractdetailsmutation.py
contract/migrations/0013_auto_20210202_0815.py
contract/migrations/0014_auto_20210208_1236.py
contract/migrations/0015_auto_20210208_1506.py
contract/migrations/0016_auto_20210208_1508.py
contract/migrations/0017_contract_roles_for_admin.py
contract/migrations/0018_approve_ask_for_change_perms.py
contract/migrations/0019_amend_perms.py
contract/migrations/0020_auto_20230126_0903.py
contract/migrations/0021_alter_contract_date_created_and_more.py
contract/migrations/0022_add_admin_rights.py
contract/migrations/0023_contractcontributionplandetails_amount_and_more.py
contract/migrations/__init__.py
contract/tests/__init__.py
contract/tests/helpers.py
contract/tests/test_helpers.py
contract/tests/test_mutation_create_tests.py
contract/tests/test_services.py
contract/tests/tests_gql_query.py
openimis_be_contract-1.10.0.dist-info/licenses/LICENSE.md
openimis_be_contract-1.10.0.dist-info/METADATA
openimis_be_contract-1.10.0.dist-info/WHEEL
openimis_be_contract-1.10.0.dist-info/top_level.txt
openimis_be_contract-1.10.0.dist-info/RECORD
